{
  "fileType": "Plan",
  "geoFence": {},
  "groundStation": "QGroundControl",
  "mission": {
    "cruiseSpeed": 15,
    "firmwareType": 12,
    "hoverSpeed": 5,
    "items": [
      {
        "autoContinue": true,
        "command": 178,
        "doJumpId": 1,
        "frame": 2,
        "params": [
          1,
          5,
          -1,
          0,
          0,
          0,
          0
        ],
        "type": "SimpleItem"
      },
      {
        "autoContinue": true,
        "command": 22,
        "doJumpId": 2,
        "frame": 3,
        "params": [
          15,
          0,
          0,
          null,
          27.683244794258535,
          85.322089849588,
          10
        ],
        "type": "SimpleItem"
      },
      {
        "autoContinue": true,
        "command": 16,
        "doJumpId": 3,
        "frame": 3,
        "params": [
          0,
          0,
          0,
          null,
          27.68334208201988,
          85.32149138832301,
          10
        ],
        "type": "SimpleItem"
      },
      {
        "autoContinue": true,
        "command": 16,
        "doJumpId": 4,
        "frame": 3,
        "params": [
          0,
          0,
          0,
          null,
          27.68270941127074,
          85.32214784098812,
          10
        ],
        "type": "SimpleItem"
      },
      {
        "autoContinue": true,
        "command": 16,
        "doJumpId": 5,
        "frame": 3,
        "params": [
          0,
          0,
          0,
          null,
          27.68310984458982,
          85.32273511022856,
          10
        ],
        "type": "SimpleItem"
      },
      {
        "autoContinue": true,
        "command": 16,
        "doJumpId": 6,
        "frame": 3,
        "params": [
          0,
          0,
          0,
          null,
          27.68374436077312,
          85.32211199521453,
          10
        ],
        "type": "SimpleItem"
      },
      {
        "autoContinue": true,
        "command": 21,
        "doJumpId": 7,
        "frame": 3,
        "params": [
          25,
          0,
          0,
          null,
          27.68330172,
          85.32210784,
          0
        ],
        "type": "SimpleItem"
      },
      {
        "autoContinue": true,
        "command": 93,
        "doJumpId": 8,
        "frame": 2,
        "params": [
          30,
          0,
          0,
          0,
          27.68330432342159,
          85.32210888104964,
          50
        ],
        "type": "SimpleItem"
      },
      {
        "autoContinue": true,
        "command": 22,
        "doJumpId": 9,
        "frame": 3,
        "params": [
          15,
          0,
          0,
          null,
          27.683299157111257,
          85.32210888184926,
          10
        ],
        "type": "SimpleItem"
      },
      {
        "autoContinue": true,
        "command": 16,
        "doJumpId": 10,
        "frame": 3,
        "params": [
          0,
          0,
          0,
          null,
          27.683288832659272,
          85.32171828461054,
          15
        ],
        "type": "SimpleItem"
      },
      {
        "autoContinue": true,
        "command": 16,
        "doJumpId": 11,
        "frame": 3,
        "params": [
          0,
          0,
          0,
          null,
          27.6829532828605,
          85.32211762120772,
          10
        ],
        "type": "SimpleItem"
      },
      {
        "autoContinue": true,
        "command": 16,
        "doJumpId": 12,
        "frame": 3,
        "params": [
          0,
          0,
          0,
          null,
          27.683185593059616,
          85.3224761509095,
          15
        ],
        "type": "SimpleItem"
      },
      {
        "autoContinue": true,
        "command": 16,
        "doJumpId": 13,
        "frame": 3,
        "params": [
          0,
          0,
          0,
          null,
          27.68357277,
          85.32211179,
          10
        ],
        "type": "SimpleItem"
      },
      {
        "autoContinue": true,
        "command": 21,
        "doJumpId": 14,
        "frame": 3,
        "params": [
          25,
          0,
          0,
          null,
          27.68342306,
          85.32196605,
          0
        ],
        "type": "SimpleItem"
      }
    ],
    "plannedHomePosition": [
      27.683244855764176,
      85.3220754585688,
      10
    ],
    "vehicleType": 2,
    "version": 2
  },
  "rallyPoints": {
    "points": [],
    "version": 1
  },
  "version": 1
}